{
    "status": "VOR", 
    "article-type": "correction", 
    "contributors": [
        {
            "type": "author", 
            "given-names": "Sezgi", 
            "surname": "Goksan", 
            "references": {
                "competing-interest": [
                    "conf1"
                ]
            }
        }, 
        {
            "orcid": "http://orcid.org/0000-0002-7981-0836", 
            "type": "author", 
            "given-names": "Caroline", 
            "surname": "Hartley", 
            "references": {
                "competing-interest": [
                    "conf1"
                ]
            }
        }, 
        {
            "type": "author", 
            "given-names": "Faith", 
            "surname": "Emery", 
            "references": {
                "competing-interest": [
                    "conf1"
                ]
            }
        }, 
        {
            "type": "author", 
            "given-names": "Naomi", 
            "surname": "Cockrill", 
            "references": {
                "competing-interest": [
                    "conf1"
                ]
            }
        }, 
        {
            "type": "author", 
            "given-names": "Ravi", 
            "surname": "Poorun", 
            "references": {
                "competing-interest": [
                    "conf1"
                ]
            }
        }, 
        {
            "type": "author", 
            "given-names": "Fiona", 
            "surname": "Moultrie", 
            "references": {
                "competing-interest": [
                    "conf1"
                ]
            }
        }, 
        {
            "type": "author", 
            "given-names": "Richard", 
            "surname": "Rogers", 
            "references": {
                "competing-interest": [
                    "conf1"
                ]
            }
        }, 
        {
            "type": "author", 
            "given-names": "Jon", 
            "surname": "Campbell", 
            "references": {
                "competing-interest": [
                    "conf1"
                ]
            }
        }, 
        {
            "type": "author", 
            "given-names": "Michael", 
            "surname": "Sanders", 
            "references": {
                "competing-interest": [
                    "conf1"
                ]
            }
        }, 
        {
            "type": "author", 
            "given-names": "Eleri", 
            "surname": "Adams", 
            "references": {
                "competing-interest": [
                    "conf1"
                ]
            }
        }, 
        {
            "type": "author", 
            "given-names": "Stuart", 
            "surname": "Clare", 
            "references": {
                "competing-interest": [
                    "conf1"
                ]
            }
        }, 
        {
            "type": "author", 
            "given-names": "Mark", 
            "surname": "Jenkinson", 
            "references": {
                "competing-interest": [
                    "conf1"
                ]
            }
        }, 
        {
            "type": "author", 
            "given-names": "Irene", 
            "surname": "Tracey", 
            "references": {
                "competing-interest": [
                    "conf1"
                ]
            }
        }, 
        {
            "corresp": true, 
            "given-names": "Rebeccah", 
            "surname": "Slater", 
            "references": {
                "competing-interest": [
                    "conf1"
                ]
            }, 
            "type": "author"
        }
    ], 
    "pub-date": "2015-05-28T00:00:00Z", 
    "title": "Correction: fMRI reveals neural activity overlap between adult and infant pain", 
    "article-id": "08663", 
    "related-articles": [
        {
            "href": "10.7554/eLife.06356", 
            "type": "corrected-article"
        }
    ], 
    "publish": true, 
    "article-version-id": "08663.1", 
    "volume": 4, 
    "doi": "10.7554/eLife.08663", 
    "version": 1, 
    "referenced": {
        "competing-interest": {
            "conf1": "The authors declare that no competing interests exist."
        }
    }, 
    "path": "content/4/e08663v1", 
    "elocation-id": "e08663", 
    "categories": {
        "heading": [
            "Neuroscience"
        ], 
        "display-channel": [
            "Correction"
        ]
    }
}
