{
    "status": "VOR", 
    "article-type": "correction", 
    "force": "1", 
    "contributors": [
        {
            "corresp": "yes", 
            "given-names": "Thomas", 
            "surname": "House", 
            "references": {
                "competing-interest": [
                    "conf1"
                ]
            }, 
            "type": "author"
        }
    ], 
    "pub-date": "2014-11-07", 
    "title": "Correction: Epidemiological dynamics of Ebola outbreaks", 
    "citations": {}, 
    "impact-statement": "", 
    "related-articles": [
        {
            "href": "10.7554/eLife.03908", 
            "type": "corrected-article"
        }
    ], 
    "elocation-id": "e05419", 
    "publish": "1", 
    "article-version-id": "05419.1", 
    "volume": "3", 
    "keywords": {}, 
    "doi": "10.7554/eLife.05419", 
    "version": "1", 
    "referenced": {
        "present-address": {}, 
        "competing-interest": {
            "conf1": "The author declares that no competing interests exist."
        }, 
        "funding": {}, 
        "related-object": {}, 
        "foot-note": {}, 
        "affiliation": {}, 
        "equal-contrib": {}, 
        "contribution": {}, 
        "email": {}
    }, 
    "path": "content/3/e05419v1", 
    "fragments": [], 
    "article-id": "10.7554/eLife.05419", 
    "categories": {
        "heading": [
            "Epidemiology and global health", 
            "Microbiology and infectious disease"
        ], 
        "display-channel": [
            "Correction"
        ]
    }
}
