{
    "status": "VOR", 
    "article-type": "research-article", 
    "contributors": [
        {
            "surname": "Rosello", 
            "corresp": "yes", 
            "given-names": "Alicia", 
            "references": {
                "competing-interest": [
                    "conf1"
                ], 
                "funding": [
                    "par-1"
                ], 
                "affiliation": [
                    "aff1", 
                    "aff2"
                ], 
                "equal-contrib": [
                    "equal-contrib"
                ], 
                "contribution": [
                    "con1"
                ], 
                "email": [
                    "cor1"
                ]
            }, 
            "equal-contrib": "yes", 
            "type": "author", 
            "id": "author-34361"
        }, 
        {
            "surname": "Mossoko", 
            "given-names": "Mathias", 
            "references": {
                "affiliation": [
                    "aff3"
                ], 
                "contribution": [
                    "con3"
                ], 
                "competing-interest": [
                    "conf1"
                ], 
                "funding": [
                    "par-1"
                ], 
                "equal-contrib": [
                    "equal-contrib"
                ]
            }, 
            "equal-contrib": "yes", 
            "type": "author", 
            "id": "author-35620"
        }, 
        {
            "type": "author", 
            "given-names": "Stefan", 
            "surname": "Flasche", 
            "id": "author-35621", 
            "references": {
                "affiliation": [
                    "aff4"
                ], 
                "contribution": [
                    "con6"
                ], 
                "competing-interest": [
                    "conf1"
                ], 
                "funding": [
                    "par-3"
                ]
            }
        }, 
        {
            "type": "author", 
            "given-names": "Albert Jan", 
            "surname": "Van Hoek", 
            "id": "author-35622", 
            "references": {
                "affiliation": [
                    "aff4"
                ], 
                "contribution": [
                    "con7"
                ], 
                "competing-interest": [
                    "conf1"
                ], 
                "funding": [
                    "par-2"
                ]
            }
        }, 
        {
            "type": "author", 
            "given-names": "Placide", 
            "surname": "Mbala", 
            "id": "author-35623", 
            "references": {
                "affiliation": [
                    "aff5"
                ], 
                "contribution": [
                    "con4"
                ], 
                "competing-interest": [
                    "conf1"
                ], 
                "funding": [
                    "par-1"
                ]
            }
        }, 
        {
            "type": "author", 
            "given-names": "Anton", 
            "surname": "Camacho", 
            "id": "author-35624", 
            "references": {
                "affiliation": [
                    "aff4"
                ], 
                "contribution": [
                    "con8"
                ], 
                "competing-interest": [
                    "conf1"
                ], 
                "funding": [
                    "par-3"
                ]
            }
        }, 
        {
            "type": "author", 
            "given-names": "Sebastian", 
            "surname": "Funk", 
            "id": "author-18737", 
            "references": {
                "affiliation": [
                    "aff4"
                ], 
                "contribution": [
                    "con9"
                ], 
                "competing-interest": [
                    "conf1"
                ], 
                "funding": [
                    "par-3"
                ]
            }
        }, 
        {
            "type": "author", 
            "given-names": "Adam", 
            "surname": "Kucharski", 
            "id": "author-21671", 
            "references": {
                "affiliation": [
                    "aff4"
                ], 
                "contribution": [
                    "con10"
                ], 
                "competing-interest": [
                    "conf1"
                ], 
                "funding": [
                    "par-3"
                ]
            }
        }, 
        {
            "type": "author", 
            "given-names": "Benoit Kebela", 
            "surname": "Ilunga", 
            "id": "author-35625", 
            "references": {
                "affiliation": [
                    "aff3"
                ], 
                "contribution": [
                    "con5"
                ], 
                "competing-interest": [
                    "conf1"
                ]
            }
        }, 
        {
            "type": "author", 
            "given-names": "W John", 
            "surname": "Edmunds", 
            "id": "author-35626", 
            "references": {
                "affiliation": [
                    "aff4"
                ], 
                "contribution": [
                    "con11"
                ], 
                "competing-interest": [
                    "conf1"
                ]
            }
        }, 
        {
            "type": "author", 
            "given-names": "Peter", 
            "surname": "Piot", 
            "id": "author-17738", 
            "references": {
                "affiliation": [
                    "aff4"
                ], 
                "contribution": [
                    "con12"
                ], 
                "competing-interest": [
                    "conf1"
                ]
            }
        }, 
        {
            "surname": "Baguelin", 
            "corresp": "yes", 
            "given-names": "Marc", 
            "references": {
                "affiliation": [
                    "aff1", 
                    "aff4"
                ], 
                "contribution": [
                    "con2"
                ], 
                "competing-interest": [
                    "conf1"
                ], 
                "funding": [
                    "par-1", 
                    "par-2"
                ], 
                "email": [
                    "cor2"
                ]
            }, 
            "type": "author", 
            "id": "author-35627"
        }, 
        {
            "type": "author", 
            "given-names": "Jean-Jacques", 
            "surname": "Muyembe Tamfum", 
            "id": "author-35628", 
            "references": {
                "affiliation": [
                    "aff5"
                ], 
                "contribution": [
                    "con13"
                ], 
                "competing-interest": [
                    "conf1"
                ], 
                "funding": [
                    "par-1"
                ]
            }
        }, 
        {
            "surname": "Abdool Karim", 
            "affiliations": [
                {
                    "country": "South Africa", 
                    "institution": "University of KwaZulu Natal"
                }
            ], 
            "given-names": "Quarraisha", 
            "role": "Reviewing editor", 
            "type": "editor", 
            "id": "author-12045"
        }
    ], 
    "pub-date": "2015-11-03", 
    "title": "Ebola virus disease in the Democratic Republic of the Congo, 1976-2014", 
    "citations": {
        "bib9": {
            "source": "The New England Journal of Medicine", 
            "doi": "10.1056/NEJMp1508413", 
            "year": "2015", 
            "title": "Community trust and the ebola endgame", 
            "authors": [
                {
                    "group-type": "author", 
                    "given-names": "RS", 
                    "surname": "Dhillon"
                }, 
                {
                    "group-type": "author", 
                    "given-names": "JD", 
                    "surname": "Kelly"
                }
            ]
        }, 
        "bib8": {
            "source": "Journal of Theoretical Biology", 
            "doi": "10.1016/j.jtbi.2004.03.006", 
            "year": "2004", 
            "title": "The basic reproductive number of Ebola and the effects of public health measures: the cases of Congo and Uganda", 
            "authors": [
                {
                    "group-type": "author", 
                    "given-names": "G", 
                    "surname": "Chowell"
                }, 
                {
                    "group-type": "author", 
                    "given-names": "NW", 
                    "surname": "Hengartner"
                }, 
                {
                    "group-type": "author", 
                    "given-names": "C", 
                    "surname": "Castillo-Chavez"
                }, 
                {
                    "group-type": "author", 
                    "given-names": "PW", 
                    "surname": "Fenimore"
                }, 
                {
                    "group-type": "author", 
                    "given-names": "JM", 
                    "surname": "Hyman"
                }
            ]
        }, 
        "bib1": {
            "source": "PLOS Current Outbreaks", 
            "doi": "10.1371/currents.outbreaks.91afb5e0f279e7f29e7056095255b288", 
            "year": "2014", 
            "title": "Estimating the reproduction number of ebola virus (EBOV) during the 2014 outbreak in west africa", 
            "authors": [
                {
                    "group-type": "author", 
                    "given-names": "C", 
                    "surname": "Althaus"
                }
            ]
        }, 
        "bib2": {
            "source": "The New England Journal of Medicine", 
            "doi": "10.1056/NEJMc1415318", 
            "year": "2015", 
            "title": "Ebola virus disease among children in West Africa", 
            "authors": [
                {
                    "group-type": "author", 
                    "collab": "WHO Ebola Response Team"
                }, 
                {
                    "group-type": "author", 
                    "given-names": "J", 
                    "surname": "Agua-Agum"
                }, 
                {
                    "group-type": "author", 
                    "given-names": "A", 
                    "surname": "Ariyarajah"
                }, 
                {
                    "group-type": "author", 
                    "given-names": "IM", 
                    "surname": "Blake"
                }, 
                {
                    "group-type": "author", 
                    "given-names": "A", 
                    "surname": "Cori"
                }, 
                {
                    "group-type": "author", 
                    "given-names": "CA", 
                    "surname": "Donnelly"
                }, 
                {
                    "group-type": "author", 
                    "given-names": "I", 
                    "surname": "Dorigatti"
                }, 
                {
                    "group-type": "author", 
                    "given-names": "C", 
                    "surname": "Dye"
                }, 
                {
                    "group-type": "author", 
                    "given-names": "T", 
                    "surname": "Eckmanns"
                }, 
                {
                    "group-type": "author", 
                    "given-names": "NM", 
                    "surname": "Ferguson"
                }, 
                {
                    "group-type": "author", 
                    "given-names": "RA", 
                    "surname": "Fowler"
                }, 
                {
                    "group-type": "author", 
                    "given-names": "C", 
                    "surname": "Fraser"
                }, 
                {
                    "group-type": "author", 
                    "given-names": "T", 
                    "surname": "Garske"
                }, 
                {
                    "group-type": "author", 
                    "given-names": "W", 
                    "surname": "Hinsley"
                }, 
                {
                    "group-type": "author", 
                    "given-names": "T", 
                    "surname": "Jombart"
                }, 
                {
                    "group-type": "author", 
                    "given-names": "HL", 
                    "surname": "Mills"
                }, 
                {
                    "group-type": "author", 
                    "given-names": "S", 
                    "surname": "Murthy"
                }, 
                {
                    "group-type": "author", 
                    "given-names": "G", 
                    "surname": "Nedjati Gilani"
                }, 
                {
                    "group-type": "author", 
                    "given-names": "P", 
                    "surname": "Nouvellet"
                }, 
                {
                    "group-type": "author", 
                    "given-names": "L", 
                    "surname": "Pelletier"
                }, 
                {
                    "group-type": "author", 
                    "given-names": "S", 
                    "surname": "Riley"
                }, 
                {
                    "group-type": "author", 
                    "given-names": "D", 
                    "surname": "Schumacher"
                }, 
                {
                    "group-type": "author", 
                    "given-names": "A", 
                    "surname": "Shah"
                }, 
                {
                    "group-type": "author", 
                    "given-names": "MD", 
                    "surname": "Van Kerkhove"
                }
            ]
        }, 
        "bib5": {
            "source": "The Journal of Infectious Diseases", 
            "doi": "10.1086/514309", 
            "year": "1999", 
            "title": "Prevalence of IgG antibodies to Ebola virus in individuals during an Ebola outbreak, Democratic Republic of the Congo, 1995", 
            "authors": [
                {
                    "group-type": "author", 
                    "given-names": "KM", 
                    "surname": "Busico"
                }, 
                {
                    "group-type": "author", 
                    "given-names": "KL", 
                    "surname": "Marshall"
                }, 
                {
                    "group-type": "author", 
                    "given-names": "TG", 
                    "surname": "Ksiazek"
                }, 
                {
                    "group-type": "author", 
                    "given-names": "TH", 
                    "surname": "Roels"
                }, 
                {
                    "group-type": "author", 
                    "given-names": "Y", 
                    "surname": "Fleerackers"
                }, 
                {
                    "group-type": "author", 
                    "given-names": "H", 
                    "surname": "Feldmann"
                }, 
                {
                    "group-type": "author", 
                    "given-names": "AS", 
                    "surname": "Khan"
                }, 
                {
                    "group-type": "author", 
                    "given-names": "CJ", 
                    "surname": "Peters"
                }
            ]
        }, 
        "bib4": {
            "source": "Ebola virus haemorrhagic fever", 
            "year": "1978", 
            "title": "The epidemiology of Ebola haemorrhagic fever in Zaire, 1976", 
            "authors": [
                {
                    "group-type": "author", 
                    "given-names": "JG", 
                    "surname": "Breman"
                }, 
                {
                    "group-type": "author", 
                    "given-names": "P", 
                    "surname": "Piot"
                }, 
                {
                    "group-type": "author", 
                    "given-names": "KM", 
                    "surname": "Johnson"
                }, 
                {
                    "group-type": "author", 
                    "given-names": "MK", 
                    "surname": "White"
                }, 
                {
                    "group-type": "author", 
                    "given-names": "M", 
                    "surname": "Mbuyi"
                }, 
                {
                    "group-type": "author", 
                    "given-names": "P", 
                    "surname": "Sureau"
                }, 
                {
                    "group-type": "author", 
                    "given-names": "DL", 
                    "surname": "Heymann"
                }, 
                {
                    "group-type": "author", 
                    "given-names": "S", 
                    "surname": "Van Nieuwenhove"
                }, 
                {
                    "group-type": "author", 
                    "given-names": "JB", 
                    "surname": "Mccormick"
                }, 
                {
                    "group-type": "author", 
                    "given-names": "JP", 
                    "surname": "Ruppol"
                }, 
                {
                    "group-type": "author", 
                    "given-names": "V", 
                    "surname": "Kintoki"
                }, 
                {
                    "group-type": "author", 
                    "given-names": "M", 
                    "surname": "Isaacson"
                }, 
                {
                    "group-type": "author", 
                    "given-names": "G", 
                    "surname": "Van Der Groen"
                }, 
                {
                    "group-type": "author", 
                    "given-names": "PA", 
                    "surname": "Webb"
                }, 
                {
                    "group-type": "author", 
                    "given-names": "K", 
                    "surname": "Ngvete"
                }, 
                {
                    "group-type": "editor", 
                    "given-names": "S", 
                    "surname": "Pattyn"
                }
            ]
        }, 
        "bib7": {
            "source": "Epidemics", 
            "doi": "10.1016/j.epidem.2014.09.003", 
            "year": "2014", 
            "title": "Potential for large outbreaks of Ebola virus disease", 
            "authors": [
                {
                    "group-type": "author", 
                    "given-names": "A", 
                    "surname": "Camacho"
                }, 
                {
                    "group-type": "author", 
                    "given-names": "AJ", 
                    "surname": "Kucharski"
                }, 
                {
                    "group-type": "author", 
                    "given-names": "S", 
                    "surname": "Funk"
                }, 
                {
                    "group-type": "author", 
                    "given-names": "J", 
                    "surname": "Breman"
                }, 
                {
                    "group-type": "author", 
                    "given-names": "P", 
                    "surname": "Piot"
                }, 
                {
                    "group-type": "author", 
                    "given-names": "WJ", 
                    "surname": "Edmunds"
                }
            ]
        }, 
        "bib6": {
            "source": "The Journal of Infectious Diseases", 
            "doi": "10.1086/514308", 
            "year": "1999", 
            "title": "Ebola hemorrhagic fever in Kikwit, Democratic Republic of the Congo: clinical observations in 103 patients", 
            "authors": [
                {
                    "group-type": "author", 
                    "given-names": "MA", 
                    "surname": "Bwaka"
                }, 
                {
                    "group-type": "author", 
                    "given-names": "MJ", 
                    "surname": "Bonnet"
                }, 
                {
                    "group-type": "author", 
                    "given-names": "P", 
                    "surname": "Calain"
                }, 
                {
                    "group-type": "author", 
                    "given-names": "R", 
                    "surname": "Colebunders"
                }, 
                {
                    "group-type": "author", 
                    "given-names": "A", 
                    "surname": "De Roo"
                }, 
                {
                    "group-type": "author", 
                    "given-names": "Y", 
                    "surname": "Guimard"
                }, 
                {
                    "group-type": "author", 
                    "given-names": "KR", 
                    "surname": "Katwiki"
                }, 
                {
                    "group-type": "author", 
                    "given-names": "K", 
                    "surname": "Kibadi"
                }, 
                {
                    "group-type": "author", 
                    "given-names": "MA", 
                    "surname": "Kipasa"
                }, 
                {
                    "group-type": "author", 
                    "given-names": "KJ", 
                    "surname": "Kuvula"
                }, 
                {
                    "group-type": "author", 
                    "given-names": "BB", 
                    "surname": "Mapanda"
                }, 
                {
                    "group-type": "author", 
                    "given-names": "M", 
                    "surname": "Massamba"
                }, 
                {
                    "group-type": "author", 
                    "given-names": "KD", 
                    "surname": "Mupapa"
                }, 
                {
                    "group-type": "author", 
                    "given-names": "JJ", 
                    "surname": "Muyembe-Tamfum"
                }, 
                {
                    "group-type": "author", 
                    "given-names": "E", 
                    "surname": "Ndaberey"
                }, 
                {
                    "group-type": "author", 
                    "given-names": "CJ", 
                    "surname": "Peters"
                }, 
                {
                    "group-type": "author", 
                    "given-names": "PE", 
                    "surname": "Rollin"
                }, 
                {
                    "group-type": "author", 
                    "given-names": "E", 
                    "surname": "Van den Enden"
                }, 
                {
                    "group-type": "author", 
                    "given-names": "E", 
                    "surname": "Van den Enden"
                }
            ]
        }, 
        "bib28": {
            "source": "The Journal of Infectious Diseases", 
            "year": "1999", 
            "title": "Epidemiologic and clinical aspects of the Ebola virus epidemic in Mosango, Democratic Republic of the Congo, 1995", 
            "authors": [
                {
                    "group-type": "author", 
                    "given-names": "R", 
                    "surname": "Ndambi"
                }, 
                {
                    "group-type": "author", 
                    "given-names": "P", 
                    "surname": "Akamituna"
                }, 
                {
                    "group-type": "author", 
                    "given-names": "MJ", 
                    "surname": "Bonnet"
                }, 
                {
                    "group-type": "author", 
                    "given-names": "AM", 
                    "surname": "Tukadila"
                }, 
                {
                    "group-type": "author", 
                    "given-names": "JJ", 
                    "surname": "Muyembe-Tamfum"
                }, 
                {
                    "group-type": "author", 
                    "given-names": "R", 
                    "surname": "Colebunders"
                }
            ]
        }, 
        "bib29": {
            "source": "Afrika Matematika", 
            "doi": "10.1007/s13370-011-0039-5", 
            "year": "2011", 
            "title": "Statistical data analysis of the 1995 Ebola outbreak in the Democratic Republic of Congo", 
            "authors": [
                {
                    "group-type": "author", 
                    "given-names": "D", 
                    "surname": "Ndanguza"
                }, 
                {
                    "group-type": "author", 
                    "given-names": "JM", 
                    "surname": "Tchuenche"
                }, 
                {
                    "group-type": "author", 
                    "given-names": "H", 
                    "surname": "Haario"
                }
            ]
        }, 
        "bib38": {
            "source": "Case definition recommendations for Ebola or Marburg virus diseases", 
            "authors": [
                {
                    "group-type": "author", 
                    "collab": "World Health Organization"
                }
            ], 
            "year": "2014"
        }, 
        "bib20": {
            "source": "The New England Journal of Medicine", 
            "doi": "10.1056/NEJMoa1411099", 
            "year": "2014", 
            "title": "Ebola virus disease in the democratic Republic of Congo", 
            "authors": [
                {
                    "group-type": "author", 
                    "given-names": "GD", 
                    "surname": "Maganga"
                }, 
                {
                    "group-type": "author", 
                    "given-names": "J", 
                    "surname": "Kapetshi"
                }, 
                {
                    "group-type": "author", 
                    "given-names": "N", 
                    "surname": "Berthet"
                }, 
                {
                    "group-type": "author", 
                    "given-names": "B", 
                    "surname": "Kebela Ilunga"
                }, 
                {
                    "group-type": "author", 
                    "given-names": "F", 
                    "surname": "Kabange"
                }, 
                {
                    "group-type": "author", 
                    "given-names": "P", 
                    "surname": "Mbala Kingebeni"
                }, 
                {
                    "group-type": "author", 
                    "given-names": "V", 
                    "surname": "Mondonge"
                }, 
                {
                    "group-type": "author", 
                    "given-names": "JJ", 
                    "surname": "Muyembe"
                }, 
                {
                    "group-type": "author", 
                    "given-names": "E", 
                    "surname": "Bertherat"
                }, 
                {
                    "group-type": "author", 
                    "given-names": "S", 
                    "surname": "Briand"
                }, 
                {
                    "group-type": "author", 
                    "given-names": "J", 
                    "surname": "Cabore"
                }, 
                {
                    "group-type": "author", 
                    "given-names": "A", 
                    "surname": "Epelboin"
                }, 
                {
                    "group-type": "author", 
                    "given-names": "P", 
                    "surname": "Formenty"
                }, 
                {
                    "group-type": "author", 
                    "given-names": "G", 
                    "surname": "Kobinger"
                }, 
                {
                    "group-type": "author", 
                    "given-names": "L", 
                    "surname": "Gonz\u00e1lez-Angulo"
                }, 
                {
                    "group-type": "author", 
                    "given-names": "I", 
                    "surname": "Labouba"
                }, 
                {
                    "group-type": "author", 
                    "given-names": "JC", 
                    "surname": "Manuguerra"
                }, 
                {
                    "group-type": "author", 
                    "given-names": "JM", 
                    "surname": "Okwo-Bele"
                }, 
                {
                    "group-type": "author", 
                    "given-names": "C", 
                    "surname": "Dye"
                }, 
                {
                    "group-type": "author", 
                    "given-names": "EM", 
                    "surname": "Leroy"
                }
            ]
        }, 
        "bib21": {
            "source": "Rapport de Mission. Riposte Contre l\u2019Epid\u00e9mie de la Maladie a Virus Ebola. Lieu: Boende (Province de l'Equateur, RDC)", 
            "authors": [
                {
                    "group-type": "author", 
                    "collab": "Minist\u00e8re de la Sant\u00e9 Publique (Comit\u00e9 National de Coordination)"
                }
            ], 
            "year": "2014"
        }, 
        "bib22": {
            "source": "Epid\u00e9mie de Fi\u00e8vre H\u00e9morragique \u00e0 Virus Ebola \u00e0 Mweka (R\u00e9publique D\u00e9mocratique du Congo)", 
            "authors": [
                {
                    "group-type": "author", 
                    "collab": "Minist\u00e8re de la Sant\u00e9 Publique (Direction de la Lutte contre la Maladie)"
                }
            ], 
            "year": "2007"
        }, 
        "bib23": {
            "source": "Rapport de la Gestion de l\u2019Epid\u00e9mie de Fi\u00e8vre H\u00e9morragique Virale Ebola dans la Zone de Sant\u00e9 de Mweka, Province du Kasai Occidental", 
            "authors": [
                {
                    "group-type": "author", 
                    "collab": "Minist\u00e8re de la Sant\u00e9 Publique (Direction de la Lutte contre la Maladie)"
                }
            ], 
            "year": "2009"
        }, 
        "bib24": {
            "source": "Gestion de l\u2019Epid\u00e9mie de la Fi\u00e8vre H\u00e9morragique a Virus Ebola a Isiro", 
            "authors": [
                {
                    "group-type": "author", 
                    "collab": "Minist\u00e8re de la Sant\u00e9 Publique (Direction de la Lutte contre la Maladie)"
                }
            ], 
            "year": "2012"
        }, 
        "bib25": {
            "source": "Lancet", 
            "doi": "10.1016/S0140-6736(95)92640-2", 
            "year": "1995", 
            "title": "Ebola haemorrhagic fever in Kikwit, Zaire", 
            "authors": [
                {
                    "group-type": "author", 
                    "given-names": "T", 
                    "surname": "Muyembe"
                }, 
                {
                    "group-type": "author", 
                    "given-names": "M", 
                    "surname": "Kipasa"
                }
            ]
        }, 
        "bib26": {
            "source": "The Journal of Infectious Diseases", 
            "doi": "10.1086/514302", 
            "year": "1999", 
            "title": "Ebola outbreak in Kikwit, Democratic Republic of the Congo: discovery and control measures", 
            "authors": [
                {
                    "group-type": "author", 
                    "given-names": "JJ", 
                    "surname": "Muyembe-Tamfum"
                }, 
                {
                    "group-type": "author", 
                    "given-names": "M", 
                    "surname": "Kipasa"
                }, 
                {
                    "group-type": "author", 
                    "given-names": "C", 
                    "surname": "Kiyungu"
                }, 
                {
                    "group-type": "author", 
                    "given-names": "R", 
                    "surname": "Colebunders"
                }
            ]
        }, 
        "bib27": {
            "source": "The Onderstepoort Journal of Veterinary Research", 
            "doi": "10.4102/ojvr.v79i2.451", 
            "year": "2012", 
            "title": "Ebola virus outbreaks in Africa: past and present", 
            "authors": [
                {
                    "group-type": "author", 
                    "given-names": "JJ", 
                    "surname": "Muyembe-Tamfum"
                }, 
                {
                    "group-type": "author", 
                    "given-names": "S", 
                    "surname": "Mulangu"
                }, 
                {
                    "group-type": "author", 
                    "given-names": "J", 
                    "surname": "Masumu"
                }, 
                {
                    "group-type": "author", 
                    "given-names": "JM", 
                    "surname": "Kayembe"
                }, 
                {
                    "group-type": "author", 
                    "given-names": "A", 
                    "surname": "Kemp"
                }, 
                {
                    "group-type": "author", 
                    "given-names": "JT", 
                    "surname": "Paweska"
                }
            ]
        }, 
        "bib1a": {
            "source": "The New England Journal of Medicine", 
            "doi": "10.1056/NEJMc1414992", 
            "year": "2015", 
            "title": "West African Ebola epidemic after one year\u2013slowing but not yet under control", 
            "authors": [
                {
                    "group-type": "author", 
                    "collab": "WHO Ebola Response Team"
                }, 
                {
                    "group-type": "author", 
                    "given-names": "J", 
                    "surname": "Agua-Agum"
                }, 
                {
                    "group-type": "author", 
                    "given-names": "A", 
                    "surname": "Ariyarajah"
                }, 
                {
                    "group-type": "author", 
                    "given-names": "B", 
                    "surname": "Aylward"
                }, 
                {
                    "group-type": "author", 
                    "given-names": "IM", 
                    "surname": "Blake"
                }, 
                {
                    "group-type": "author", 
                    "given-names": "R", 
                    "surname": "Brennan"
                }, 
                {
                    "group-type": "author", 
                    "given-names": "A", 
                    "surname": "Cori"
                }, 
                {
                    "group-type": "author", 
                    "given-names": "CA", 
                    "surname": "Donnelly"
                }, 
                {
                    "group-type": "author", 
                    "given-names": "I", 
                    "surname": "Dorigatti"
                }, 
                {
                    "group-type": "author", 
                    "given-names": "C", 
                    "surname": "Dye"
                }, 
                {
                    "group-type": "author", 
                    "given-names": "T", 
                    "surname": "Eckmanns"
                }, 
                {
                    "group-type": "author", 
                    "given-names": "NM", 
                    "surname": "Ferguson"
                }, 
                {
                    "group-type": "author", 
                    "given-names": "P", 
                    "surname": "Formenty"
                }, 
                {
                    "group-type": "author", 
                    "given-names": "C", 
                    "surname": "Fraser"
                }, 
                {
                    "group-type": "author", 
                    "given-names": "E", 
                    "surname": "Garcia"
                }, 
                {
                    "group-type": "author", 
                    "given-names": "T", 
                    "surname": "Garske"
                }, 
                {
                    "group-type": "author", 
                    "given-names": "W", 
                    "surname": "Hinsley"
                }, 
                {
                    "group-type": "author", 
                    "given-names": "D", 
                    "surname": "Holmes"
                }, 
                {
                    "group-type": "author", 
                    "given-names": "S", 
                    "surname": "Hugonnet"
                }, 
                {
                    "group-type": "author", 
                    "given-names": "S", 
                    "surname": "Iyengar"
                }, 
                {
                    "group-type": "author", 
                    "given-names": "T", 
                    "surname": "Jombart"
                }, 
                {
                    "group-type": "author", 
                    "given-names": "R", 
                    "surname": "Krishnan"
                }, 
                {
                    "group-type": "author", 
                    "given-names": "S", 
                    "surname": "Meijers"
                }, 
                {
                    "group-type": "author", 
                    "given-names": "HL", 
                    "surname": "Mills"
                }, 
                {
                    "group-type": "author", 
                    "given-names": "Y", 
                    "surname": "Mohamed"
                }, 
                {
                    "group-type": "author", 
                    "given-names": "G", 
                    "surname": "Nedjati-Gilani"
                }, 
                {
                    "group-type": "author", 
                    "given-names": "E", 
                    "surname": "Newton"
                }, 
                {
                    "group-type": "author", 
                    "given-names": "P", 
                    "surname": "Nouvellet"
                }, 
                {
                    "group-type": "author", 
                    "given-names": "L", 
                    "surname": "Pelletier"
                }, 
                {
                    "group-type": "author", 
                    "given-names": "D", 
                    "surname": "Perkins"
                }, 
                {
                    "group-type": "author", 
                    "given-names": "S", 
                    "surname": "Riley"
                }, 
                {
                    "group-type": "author", 
                    "given-names": "M", 
                    "surname": "Sagrado"
                }, 
                {
                    "group-type": "author", 
                    "given-names": "J", 
                    "surname": "Schnitzler"
                }, 
                {
                    "group-type": "author", 
                    "given-names": "D", 
                    "surname": "Schumacher"
                }, 
                {
                    "group-type": "author", 
                    "given-names": "A", 
                    "surname": "Shah"
                }, 
                {
                    "group-type": "author", 
                    "given-names": "MD", 
                    "surname": "Van Kerkhove"
                }, 
                {
                    "group-type": "author", 
                    "given-names": "O", 
                    "surname": "Varsaneux"
                }, 
                {
                    "group-type": "author", 
                    "given-names": "N", 
                    "surname": "Wijekoon Kannangarage"
                }
            ]
        }, 
        "bib11": {
            "source": "Mathematical Biosciences", 
            "doi": "10.1016/j.mbs.2005.08.002", 
            "year": "2005", 
            "title": "Estimation and inference of R0 of an infectious pathogen by a removal method", 
            "authors": [
                {
                    "group-type": "author", 
                    "given-names": "MJ", 
                    "surname": "Ferrari"
                }, 
                {
                    "group-type": "author", 
                    "given-names": "ON", 
                    "surname": "Bj\u00f8rnstad"
                }, 
                {
                    "group-type": "author", 
                    "given-names": "AP", 
                    "surname": "Dobson"
                }
            ]
        }, 
        "bib10": {
            "source": "The Lancet Infectious Diseases", 
            "doi": "10.1016/S1473-3099(14)71075-8", 
            "year": "2015", 
            "title": "Chains of transmission and control of Ebola virus disease in Conakry, Guinea, in 2014: an observational study", 
            "authors": [
                {
                    "group-type": "author", 
                    "given-names": "O", 
                    "surname": "Faye"
                }, 
                {
                    "group-type": "author", 
                    "given-names": "PY", 
                    "surname": "Bo\u00eblle"
                }, 
                {
                    "group-type": "author", 
                    "given-names": "E", 
                    "surname": "Heleze"
                }, 
                {
                    "group-type": "author", 
                    "given-names": "O", 
                    "surname": "Faye"
                }, 
                {
                    "group-type": "author", 
                    "given-names": "C", 
                    "surname": "Loucoubar"
                }, 
                {
                    "group-type": "author", 
                    "given-names": "N", 
                    "surname": "Magassouba"
                }, 
                {
                    "group-type": "author", 
                    "given-names": "B", 
                    "surname": "Soropogui"
                }, 
                {
                    "group-type": "author", 
                    "given-names": "S", 
                    "surname": "Keita"
                }, 
                {
                    "group-type": "author", 
                    "given-names": "T", 
                    "surname": "Gakou"
                }, 
                {
                    "group-type": "author", 
                    "given-names": "HI", 
                    "surname": "Bah el"
                }, 
                {
                    "group-type": "author", 
                    "given-names": "L", 
                    "surname": "Koivogui"
                }, 
                {
                    "group-type": "author", 
                    "given-names": "AA", 
                    "surname": "Sall"
                }, 
                {
                    "group-type": "author", 
                    "given-names": "S", 
                    "surname": "Cauchemez"
                }
            ]
        }, 
        "bib13": {
            "source": "The Journal of Infectious Diseases", 
            "doi": "10.1093/infdis/142.3.372", 
            "year": "1980", 
            "title": "Ebola hemorrhagic fever: Tandala, Zaire, 1977\u20131978", 
            "authors": [
                {
                    "group-type": "author", 
                    "given-names": "DL", 
                    "surname": "Heymann"
                }, 
                {
                    "group-type": "author", 
                    "given-names": "JS", 
                    "surname": "Weisfeld"
                }, 
                {
                    "group-type": "author", 
                    "given-names": "PA", 
                    "surname": "Webb"
                }, 
                {
                    "group-type": "author", 
                    "given-names": "KM", 
                    "surname": "Johnson"
                }, 
                {
                    "group-type": "author", 
                    "given-names": "T", 
                    "surname": "Cairns"
                }, 
                {
                    "group-type": "author", 
                    "given-names": "H", 
                    "surname": "Berquist"
                }
            ]
        }, 
        "bib12": {
            "source": "Statistics in Medicine", 
            "doi": "10.1002/sim.3136", 
            "year": "2008", 
            "title": "A likelihood\u2010based method for real\u2010time estimation of the serial interval and reproductive number of an epidemic", 
            "authors": [
                {
                    "group-type": "author", 
                    "given-names": "L", 
                    "surname": "Forsberg White"
                }, 
                {
                    "group-type": "author", 
                    "given-names": "M", 
                    "surname": "Pagano"
                }
            ]
        }, 
        "bib15": {
            "source": "The Journal of Infectious Diseases", 
            "doi": "10.1086/514306", 
            "year": "1999", 
            "title": "The reemergence of Ebola hemorrhagic fever, Democratic Republic of the Congo, 1995", 
            "authors": [
                {
                    "group-type": "author", 
                    "given-names": "AS", 
                    "surname": "Khan"
                }, 
                {
                    "group-type": "author", 
                    "given-names": "FK", 
                    "surname": "Tshioko"
                }, 
                {
                    "group-type": "author", 
                    "given-names": "DL", 
                    "surname": "Heymann"
                }, 
                {
                    "group-type": "author", 
                    "given-names": "B", 
                    "surname": "Le Guenno"
                }, 
                {
                    "group-type": "author", 
                    "given-names": "P", 
                    "surname": "Nabeth"
                }, 
                {
                    "group-type": "author", 
                    "given-names": "B", 
                    "surname": "Kersti\u00ebns"
                }, 
                {
                    "group-type": "author", 
                    "given-names": "Y", 
                    "surname": "Fleerackers"
                }, 
                {
                    "group-type": "author", 
                    "given-names": "PH", 
                    "surname": "Kilmarx"
                }, 
                {
                    "group-type": "author", 
                    "given-names": "GR", 
                    "surname": "Rodier"
                }, 
                {
                    "group-type": "author", 
                    "given-names": "O", 
                    "surname": "Nkuku"
                }, 
                {
                    "group-type": "author", 
                    "given-names": "PE", 
                    "surname": "Rollin"
                }, 
                {
                    "group-type": "author", 
                    "given-names": "A", 
                    "surname": "Sanchez"
                }, 
                {
                    "group-type": "author", 
                    "given-names": "SR", 
                    "surname": "Zaki"
                }, 
                {
                    "group-type": "author", 
                    "given-names": "R", 
                    "surname": "Swanepoel"
                }, 
                {
                    "group-type": "author", 
                    "given-names": "O", 
                    "surname": "Tomori"
                }, 
                {
                    "group-type": "author", 
                    "given-names": "ST", 
                    "surname": "Nichol"
                }, 
                {
                    "group-type": "author", 
                    "given-names": "CJ", 
                    "surname": "Peters"
                }, 
                {
                    "group-type": "author", 
                    "given-names": "JJ", 
                    "surname": "Muyembe-Tamfum"
                }, 
                {
                    "group-type": "author", 
                    "given-names": "TG", 
                    "surname": "Ksiazek"
                }
            ]
        }, 
        "bib14": {
            "source": "The Journal of Infectious Diseases", 
            "doi": "10.1086/514295", 
            "year": "1999", 
            "title": "Ebola between outbreaks: intensified Ebola hemorrhagic fever surveillance in the Democratic Republic of the Congo, 1981-1985", 
            "authors": [
                {
                    "group-type": "author", 
                    "given-names": "Z", 
                    "surname": "Jezek"
                }, 
                {
                    "group-type": "author", 
                    "given-names": "MY", 
                    "surname": "Szczeniowski"
                }, 
                {
                    "group-type": "author", 
                    "given-names": "JJ", 
                    "surname": "Muyembe-Tamfum"
                }, 
                {
                    "group-type": "author", 
                    "given-names": "JB", 
                    "surname": "McCormick"
                }, 
                {
                    "group-type": "author", 
                    "given-names": "DL", 
                    "surname": "Heymann"
                }
            ]
        }, 
        "bib17": {
            "source": "Biometrics", 
            "doi": "10.1111/j.1541-0420.2006.00609.x", 
            "year": "2006", 
            "title": "Statistical inference in a stochastic epidemic SEIR model with control intervention: Ebola as a case study", 
            "authors": [
                {
                    "group-type": "author", 
                    "given-names": "PE", 
                    "surname": "Lekone"
                }, 
                {
                    "group-type": "author", 
                    "given-names": "BF", 
                    "surname": "Finkenst\u00e4dt"
                }
            ]
        }, 
        "bib16": {
            "source": "Epidemiology and Infection", 
            "doi": "10.1017/S0950268806007217", 
            "year": "2007", 
            "title": "Understanding the dynamics of Ebola epidemics", 
            "authors": [
                {
                    "group-type": "author", 
                    "given-names": "J", 
                    "surname": "Legrand"
                }, 
                {
                    "group-type": "author", 
                    "given-names": "RF", 
                    "surname": "Grais"
                }, 
                {
                    "group-type": "author", 
                    "given-names": "PY", 
                    "surname": "Boelle"
                }, 
                {
                    "group-type": "author", 
                    "given-names": "AJ", 
                    "surname": "Valleron"
                }, 
                {
                    "group-type": "author", 
                    "given-names": "A", 
                    "surname": "Flahault"
                }
            ]
        }, 
        "bib19": {
            "source": "Vector Borne and Zoonotic Diseases", 
            "doi": "10.1089/vbz.2008.0167", 
            "year": "2009", 
            "title": "Human Ebola outbreak resulting from direct exposure to fruit bats in Luebo, Democratic Republic of Congo, 2007", 
            "authors": [
                {
                    "group-type": "author", 
                    "given-names": "EM", 
                    "surname": "Leroy"
                }, 
                {
                    "group-type": "author", 
                    "given-names": "A", 
                    "surname": "Epelboin"
                }, 
                {
                    "group-type": "author", 
                    "given-names": "V", 
                    "surname": "Mondonge"
                }, 
                {
                    "group-type": "author", 
                    "given-names": "X", 
                    "surname": "Pourrut"
                }, 
                {
                    "group-type": "author", 
                    "given-names": "JP", 
                    "surname": "Gonzalez"
                }, 
                {
                    "group-type": "author", 
                    "given-names": "JJ", 
                    "surname": "Muyembe-Tamfum"
                }, 
                {
                    "group-type": "author", 
                    "given-names": "P", 
                    "surname": "Formenty"
                }
            ]
        }, 
        "bib18": {
            "source": "Lancet", 
            "doi": "10.1016/S0140-6736(00)02405-3", 
            "year": "2000", 
            "title": "Human asymptomatic Ebola infection and strong inflammatory response", 
            "authors": [
                {
                    "group-type": "author", 
                    "given-names": "EM", 
                    "surname": "Leroy"
                }, 
                {
                    "group-type": "author", 
                    "given-names": "S", 
                    "surname": "Baize"
                }, 
                {
                    "group-type": "author", 
                    "given-names": "VE", 
                    "surname": "Volchkov"
                }, 
                {
                    "group-type": "author", 
                    "given-names": "SP", 
                    "surname": "Fisher-Hoch"
                }, 
                {
                    "group-type": "author", 
                    "given-names": "MC", 
                    "surname": "Georges-Courbot"
                }, 
                {
                    "group-type": "author", 
                    "given-names": "J", 
                    "surname": "Lansoud-Soukate"
                }, 
                {
                    "group-type": "author", 
                    "given-names": "M", 
                    "surname": "Capron"
                }, 
                {
                    "group-type": "author", 
                    "given-names": "P", 
                    "surname": "Debr\u00e9"
                }, 
                {
                    "group-type": "author", 
                    "given-names": "JB", 
                    "surname": "McCormick"
                }, 
                {
                    "group-type": "author", 
                    "given-names": "AJ", 
                    "surname": "Georges"
                }
            ]
        }, 
        "bib35": {
            "source": "Scientific Data", 
            "doi": "10.1038/sdata.2015.19", 
            "year": "2015", 
            "title": "A review of epidemiological parameters from Ebola outbreaks to inform early public health decision-making", 
            "authors": [
                {
                    "group-type": "author", 
                    "given-names": "MD", 
                    "surname": "Van Kerkhove"
                }, 
                {
                    "group-type": "author", 
                    "given-names": "AI", 
                    "surname": "Bento"
                }, 
                {
                    "group-type": "author", 
                    "given-names": "HL", 
                    "surname": "Mills"
                }, 
                {
                    "group-type": "author", 
                    "given-names": "NM", 
                    "surname": "Ferguson"
                }, 
                {
                    "group-type": "author", 
                    "given-names": "CA", 
                    "surname": "Donnelly"
                }
            ]
        }, 
        "bib34": {
            "source": "World Population Prospects: The 2012 Revision", 
            "authors": [
                {
                    "group-type": "author", 
                    "collab": "United Nations (Department of Economic and Social Affairs)"
                }
            ], 
            "year": "2013"
        }, 
        "bib33": {
            "source": "The Journal of Infectious Diseases", 
            "doi": "10.1086/514311", 
            "year": "1999", 
            "title": "Ebola hemorrhagic fever, Democratic Republic of the Congo, 1995: determinants of survival", 
            "authors": [
                {
                    "group-type": "author", 
                    "given-names": "RF", 
                    "surname": "Sadek"
                }, 
                {
                    "group-type": "author", 
                    "given-names": "AS", 
                    "surname": "Khan"
                }, 
                {
                    "group-type": "author", 
                    "given-names": "G", 
                    "surname": "Stevens"
                }, 
                {
                    "group-type": "author", 
                    "given-names": "CJ", 
                    "surname": "Peters"
                }, 
                {
                    "group-type": "author", 
                    "given-names": "TG", 
                    "surname": "Ksiazek"
                }
            ]
        }, 
        "bib32": {
            "source": "The Journal of Infectious Diseases", 
            "doi": "10.1086/514318", 
            "year": "1999", 
            "title": "Clinical, virologic, and immunologic follow-up of convalescent Ebola hemorrhagic fever patients and their household contacts, Kikwit, Democratic Republic of the Congo", 
            "authors": [
                {
                    "group-type": "author", 
                    "given-names": "AK", 
                    "surname": "Rowe"
                }, 
                {
                    "group-type": "author", 
                    "given-names": "J", 
                    "surname": "Bertolli"
                }, 
                {
                    "group-type": "author", 
                    "given-names": "AS", 
                    "surname": "Khan"
                }, 
                {
                    "group-type": "author", 
                    "given-names": "R", 
                    "surname": "Mukunu"
                }, 
                {
                    "group-type": "author", 
                    "given-names": "JJ", 
                    "surname": "Muyembe-Tamfum"
                }, 
                {
                    "group-type": "author", 
                    "given-names": "D", 
                    "surname": "Bressler"
                }, 
                {
                    "group-type": "author", 
                    "given-names": "AJ", 
                    "surname": "Williams"
                }, 
                {
                    "group-type": "author", 
                    "given-names": "CJ", 
                    "surname": "Peters"
                }, 
                {
                    "group-type": "author", 
                    "given-names": "L", 
                    "surname": "Rodriguez"
                }, 
                {
                    "group-type": "author", 
                    "given-names": "H", 
                    "surname": "Feldmann"
                }, 
                {
                    "group-type": "author", 
                    "given-names": "ST", 
                    "surname": "Nichol"
                }, 
                {
                    "group-type": "author", 
                    "given-names": "PE", 
                    "surname": "Rollin"
                }, 
                {
                    "group-type": "author", 
                    "given-names": "TG", 
                    "surname": "Ksiazek"
                }
            ]
        }, 
        "bib31": {
            "source": "R: a language and environment for statistical computing", 
            "authors": [
                {
                    "group-type": "author", 
                    "collab": "R Development Core Team"
                }
            ], 
            "year": "2011"
        }, 
        "bib30": {
            "source": "eLife", 
            "doi": "10.7554/eLife.04395", 
            "year": "2014", 
            "title": "Mapping the zoonotic niche of Ebola virus disease in Africa", 
            "authors": [
                {
                    "group-type": "author", 
                    "given-names": "DM", 
                    "surname": "Pigott"
                }, 
                {
                    "group-type": "author", 
                    "given-names": "N", 
                    "surname": "Golding"
                }, 
                {
                    "group-type": "author", 
                    "given-names": "A", 
                    "surname": "Mylne"
                }, 
                {
                    "group-type": "author", 
                    "given-names": "Z", 
                    "surname": "Huang"
                }, 
                {
                    "group-type": "author", 
                    "given-names": "AJ", 
                    "surname": "Henry"
                }, 
                {
                    "group-type": "author", 
                    "given-names": "DJ", 
                    "surname": "Weiss"
                }, 
                {
                    "group-type": "author", 
                    "given-names": "OJ", 
                    "surname": "Brady"
                }, 
                {
                    "group-type": "author", 
                    "given-names": "MU", 
                    "surname": "Kraemer"
                }, 
                {
                    "group-type": "author", 
                    "given-names": "DL", 
                    "surname": "Smith"
                }, 
                {
                    "group-type": "author", 
                    "given-names": "CL", 
                    "surname": "Moyes"
                }, 
                {
                    "group-type": "author", 
                    "given-names": "S", 
                    "surname": "Bhatt"
                }, 
                {
                    "group-type": "author", 
                    "given-names": "PW", 
                    "surname": "Gething"
                }, 
                {
                    "group-type": "author", 
                    "given-names": "PW", 
                    "surname": "Horby"
                }, 
                {
                    "group-type": "author", 
                    "surname": "Bogoch", 
                    "suffix": "II"
                }, 
                {
                    "group-type": "author", 
                    "given-names": "JS", 
                    "surname": "Brownstein"
                }, 
                {
                    "group-type": "author", 
                    "given-names": "SR", 
                    "surname": "Mekaru"
                }, 
                {
                    "group-type": "author", 
                    "given-names": "AJ", 
                    "surname": "Tatem"
                }, 
                {
                    "group-type": "author", 
                    "given-names": "K", 
                    "surname": "Khan"
                }, 
                {
                    "group-type": "author", 
                    "given-names": "SI", 
                    "surname": "Hay"
                }
            ]
        }, 
        "bib37": {
            "source": "Bulletin of the World Health Organization", 
            "year": "1978", 
            "title": "Ebola haemorrhagic fever in Zaire, 1976", 
            "authors": [
                {
                    "group-type": "author", 
                    "collab": "World Health Organization"
                }
            ]
        }, 
        "bib36": {
            "source": "American Journal of Epidemiology", 
            "doi": "10.1093/aje/kwh255", 
            "year": "2004", 
            "title": "Different epidemic curves for severe acute respiratory syndrome reveal similar impacts of control measures", 
            "authors": [
                {
                    "group-type": "author", 
                    "given-names": "J", 
                    "surname": "Wallinga"
                }, 
                {
                    "group-type": "author", 
                    "given-names": "P", 
                    "surname": "Teunis"
                }
            ]
        }
    }, 
    "impact-statement": "Analysing a compilation of individual-level data gathered across the seven Ebola Virus Disease outbreaks in the Democratic Republic of the Congo reveals factors that contribute to the spread of the disease and mortality.", 
    "elocation-id": "e09015", 
    "publish": "1", 
    "article-version-id": "09015.1", 
    "volume": "4", 
    "keywords": {
        "author-keywords": [
            "Ebola", 
            "Democratic Republic of the Congo", 
            "outbreaks"
        ], 
        "research-organism": [
            "other"
        ]
    }, 
    "doi": "10.7554/eLife.09015", 
    "version": "1", 
    "referenced": {
        "competing-interest": {
            "conf1": "The authors declare that no competing interests exist."
        }, 
        "funding": {
            "par-3": {
                "award-id": "13165", 
                "institution": "Research for Health in Humanitarian Crises"
            }, 
            "par-2": {
                "award-id": "EPIDZD03", 
                "institution": "National Institute for Health Research Health Protection Research Unit in Immunisation at the London School of Hygiene and Tropical Medicine in partnership with Public Health England"
            }, 
            "par-1": {
                "institution": "Fischer Family Trust"
            }
        }, 
        "affiliation": {
            "aff5": {
                "country": "Democratic Republic of the Congo", 
                "institution": "Institut National de Recherche Biom\u00e9dicale", 
                "city": "Kinshasa"
            }, 
            "aff4": {
                "country": "United Kingdom", 
                "institution": "London School of Hygiene and Tropical Medicine", 
                "city": "London"
            }, 
            "aff3": {
                "country": "Democratic Republic of the Congo", 
                "institution": "Direction de lutte contre la maladie", 
                "city": "Kinshasa"
            }, 
            "aff2": {
                "country": "United Kingdom", 
                "institution": "University College London", 
                "city": "London"
            }, 
            "aff1": {
                "country": "United Kingdom", 
                "institution": "Public Health England", 
                "city": "London"
            }
        }, 
        "equal-contrib": {
            "equal-contrib": "These authors contributed equally to this work"
        }, 
        "contribution": {
            "con1": "AR, Conception and design, Acquisition of data, Analysis and interpretation of data, Drafting or revising the article", 
            "con2": "MB, Conception and design, Acquisition of data, Analysis and interpretation of data, Drafting or revising the article", 
            "con3": "MM, Acquisition of data, Drafting or revising the article", 
            "con4": "PM, Acquisition of data, Drafting or revising the article", 
            "con5": "BKI, Acquisition of data, Drafting or revising the article", 
            "con6": "SF, Analysis and interpretation of data, Drafting or revising the article", 
            "con7": "AJVH, Analysis and interpretation of data, Drafting or revising the article", 
            "con8": "AC, Analysis and interpretation of data, Drafting or revising the article", 
            "con9": "SF, Analysis and interpretation of data, Drafting or revising the article", 
            "con12": "PP, Conception and design, Analysis and interpretation of data, Drafting or revising the article", 
            "con13": "J-JMT, Conception and design, Analysis and interpretation of data, Drafting or revising the article", 
            "con10": "AK, Analysis and interpretation of data, Drafting or revising the article", 
            "con11": "WJE, Conception and design, Analysis and interpretation of data, Drafting or revising the article"
        }, 
        "email": {
            "cor1": "alicia.rosello.13@ucl.ac.uk", 
            "cor2": "marc.baguelin@lshtm.ac.uk"
        }
    }, 
    "path": "content/4/e09015v1", 
    "fragments": [
        {
            "path": "content/4/e09015v1/abstract", 
            "doi": "10.7554/eLife.09015.001", 
            "type": "abstract"
        }, 
        {
            "path": "content/4/e09015v1/abstract2", 
            "doi": "10.7554/eLife.09015.002", 
            "type": "abstract", 
            "title": "eLife digest"
        }, 
        {
            "path": "content/4/e09015v1/figure1", 
            "doi": "10.7554/eLife.09015.003", 
            "type": "fig", 
            "title": "Figure 1."
        }, 
        {
            "path": "content/4/e09015v1/table1", 
            "doi": "10.7554/eLife.09015.004", 
            "type": "table-wrap", 
            "title": "Table 1."
        }, 
        {
            "path": "content/4/e09015v1/table2", 
            "doi": "10.7554/eLife.09015.005", 
            "type": "table-wrap", 
            "title": "Table 2."
        }, 
        {
            "path": "content/4/e09015v1/figure2", 
            "doi": "10.7554/eLife.09015.006", 
            "type": "fig", 
            "title": "Figure 2."
        }, 
        {
            "path": "content/4/e09015v1/figure3", 
            "doi": "10.7554/eLife.09015.007", 
            "type": "fig", 
            "title": "Figure 3."
        }, 
        {
            "path": "content/4/e09015v1/figure4", 
            "doi": "10.7554/eLife.09015.008", 
            "type": "fig", 
            "title": "Figure 4."
        }, 
        {
            "path": "content/4/e09015v1/figure5", 
            "fragments": [
                {
                    "path": "content/4/e09015v1/figure5/figure-supp1", 
                    "doi": "10.7554/eLife.09015.010", 
                    "type": "fig", 
                    "title": "Figure 5\u2014figure supplement 1."
                }, 
                {
                    "path": "content/4/e09015v1/figure5/figure-supp2", 
                    "doi": "10.7554/eLife.09015.011", 
                    "type": "fig", 
                    "title": "Figure 5\u2014figure supplement 2."
                }
            ], 
            "doi": "10.7554/eLife.09015.009", 
            "type": "fig", 
            "title": "Figure 5."
        }, 
        {
            "path": "content/4/e09015v1/table3", 
            "doi": "10.7554/eLife.09015.012", 
            "type": "table-wrap", 
            "title": "Table 3."
        }, 
        {
            "path": "content/4/e09015v1/table4", 
            "doi": "10.7554/eLife.09015.013", 
            "type": "table-wrap", 
            "title": "Table 4."
        }, 
        {
            "path": "content/4/e09015v1/figure6", 
            "doi": "10.7554/eLife.09015.014", 
            "type": "fig", 
            "title": "Figure 6."
        }, 
        {
            "path": "content/4/e09015v1/figure7", 
            "doi": "10.7554/eLife.09015.015", 
            "type": "fig", 
            "title": "Figure 7."
        }, 
        {
            "path": "content/4/e09015v1/table5", 
            "doi": "10.7554/eLife.09015.016", 
            "type": "table-wrap", 
            "title": "Table 5."
        }, 
        {
            "path": "content/4/e09015v1/supp-material1", 
            "doi": "10.7554/eLife.09015.017", 
            "type": "supplementary-material", 
            "title": "Supplementary file 1."
        }, 
        {
            "path": "content/4/e09015v1/supp-material2", 
            "doi": "10.7554/eLife.09015.018", 
            "type": "supplementary-material", 
            "title": "Supplementary file 2."
        }, 
        {
            "path": "content/4/e09015v1/decision", 
            "doi": "10.7554/eLife.09015.019", 
            "type": "sub-article", 
            "contributors": [
                {
                    "surname": "Abdool Karim", 
                    "given-names": "Quarraisha", 
                    "role": "Reviewing editor", 
                    "affiliations": [
                        {
                            "country": "South Africa", 
                            "institution": "University of KwaZulu Natal"
                        }
                    ], 
                    "type": "editor"
                }
            ], 
            "title": "Decision letter"
        }, 
        {
            "path": "content/4/e09015v1/response", 
            "doi": "10.7554/eLife.09015.020", 
            "type": "sub-article", 
            "title": "Author response"
        }
    ], 
    "article-id": "09015", 
    "categories": {
        "heading": [
            "Epidemiology and global health"
        ], 
        "display-channel": [
            "Research article"
        ]
    }
}
