{
    "status": "VOR", 
    "article-type": "correction", 
    "contributors": [
        {
            "type": "author", 
            "given-names": "Emily R", 
            "surname": "Derbyshire", 
            "id": "author-6184", 
            "references": {
                "competing-interest": [
                    "conf2"
                ]
            }
        }, 
        {
            "type": "author", 
            "given-names": "Jon", 
            "surname": "Clardy", 
            "id": "author-1060", 
            "references": {
                "competing-interest": [
                    "conf1"
                ]
            }
        }
    ], 
    "pub-date": "2013-07-23T00:00:00Z", 
    "title": "Correction: Closing in on a new treatment for sleeping sickness", 
    "article-id": "01221", 
    "related-articles": [
        {
            "href": "10.7554/eLife.01042", 
            "type": "corrected-article"
        }
    ], 
    "publish": true, 
    "article-version-id": "01221.1", 
    "volume": 2, 
    "doi": "10.7554/eLife.01221", 
    "version": 1, 
    "referenced": {
        "competing-interest": {
            "conf2": "The other author declares that no competing interests exist.", 
            "conf1": "JC: <italic>eLife</italic> reviewing editor."
        }
    }, 
    "path": "content/2/e01221v1", 
    "elocation-id": "e01221", 
    "categories": {
        "heading": [
            "Biochemistry", 
            "Cell biology"
        ], 
        "display-channel": [
            "Correction"
        ]
    }
}
